[
 {
  "id":"m_seimeikagaku",
  "name":"生命科学研究科（修士）",
  "cycle":"master",
  "url":"https:\/\/qsl.cds.tohoku.ac.jp\/qsl\/syllabus\/find?type=seimeikagaku",
  "languages":[
   "other"
  ],
  "campuses":[

  ],
  "faculties":[
   "生命科学研究科"
  ],
  "fields":[
   "Science"
  ],
  "themes":[
   "climate",
   "environment",
   "sustainability"
  ],
  "themes_scores":[
   2,
   3,
   3
  ],
  "matched_courses":[
   "bm3032000",
   "bm3031000",
   "bm1022000",
   "bm1021000",
   "bm1012000"
  ],
  "nb_dedicated_courses":1
 },
 {
  "id":"m_jouhoukagaku",
  "name":"情報科学研究科（修士）",
  "cycle":"master",
  "url":"https:\/\/qsl.cds.tohoku.ac.jp\/qsl\/syllabus\/find?type=jouhoukagaku",
  "languages":[
   "ja",
   "other",
   "en"
  ],
  "campuses":[

  ],
  "faculties":[
   "情報科学研究科"
  ],
  "fields":[
   "Engineering"
  ],
  "themes":[
   "climate"
  ],
  "themes_scores":[
   1
  ],
  "matched_courses":[
   "im20111100"
  ],
  "nb_dedicated_courses":0
 },
 {
  "id":"m_kankyoukagaku",
  "name":"環境科学研究科（修士）",
  "cycle":"master",
  "url":"https:\/\/qsl.cds.tohoku.ac.jp\/qsl\/syllabus\/find?type=kankyoukagaku",
  "languages":[
   "ja"
  ],
  "campuses":[

  ],
  "faculties":[
   "環境科学研究科"
  ],
  "fields":[
   "Science"
  ],
  "themes":[
   "climate",
   "energy",
   "environment",
   "resources",
   "sustainability"
  ],
  "themes_scores":[
   14,
   11,
   19,
   3,
   22
  ],
  "matched_courses":[
   "gm000009",
   "gm200007",
   "gm000029",
   "gm000015",
   "gm400021",
   "gm000043",
   "gm000027",
   "gm900003",
   "gm000042",
   "gm900002",
   "gm200005",
   "gm000047",
   "gm000045",
   "gm100008",
   "gm100004",
   "gm000022",
   "gm000005",
   "gm000025",
   "gm400016",
   "gm000013",
   "gm100001",
   "gm200002",
   "gm400015",
   "gm000046",
   "gm000010",
   "gm1000012",
   "gm300001",
   "gm000021",
   "gm000011",
   "gm000002",
   "gm1000011",
   "gm000044",
   "gm000018",
   "gm000003",
   "gm200006",
   "gm400001",
   "gm000004",
   "gm000030"
  ],
  "nb_dedicated_courses":33
 },
 {
  "id":"d_kankyoukagaku",
  "name":"環境科学研究科（博士）",
  "cycle":"doctor",
  "url":"https:\/\/qsl.cds.tohoku.ac.jp\/qsl\/syllabus\/find?type=kankyoukagaku",
  "languages":[
   "ja"
  ],
  "campuses":[

  ],
  "faculties":[
   "環境科学研究科"
  ],
  "fields":[
   "Science"
  ],
  "themes":[
   "climate",
   "energy",
   "environment",
   "sustainability"
  ],
  "themes_scores":[
   3,
   2,
   1,
   5
  ],
  "matched_courses":[
   "gd000002",
   "gd200002",
   "gd100002",
   "gd400001",
   "gd000011"
  ],
  "nb_dedicated_courses":4
 },
 {
  "id":"b_hoken",
  "name":"医学部保健学科（学士）",
  "cycle":"bac",
  "url":"https:\/\/qsl.cds.tohoku.ac.jp\/qsl\/syllabus\/find?type=hoken",
  "languages":[
   "ja",
   "other"
  ],
  "campuses":[

  ],
  "faculties":[
   "医学部保健学科"
  ],
  "fields":[
   "Medecine & Health"
  ],
  "themes":[
   "climate"
  ],
  "themes_scores":[
   1
  ],
  "matched_courses":[
   "hb44411"
  ],
  "nb_dedicated_courses":1
 },
 {
  "id":"m_kokusaibunka",
  "name":"国際文化研究科（修士）",
  "cycle":"master",
  "url":"https:\/\/qsl.cds.tohoku.ac.jp\/qsl\/syllabus\/find?type=kokusaibunka",
  "languages":[
   "ja",
   "en"
  ],
  "campuses":[

  ],
  "faculties":[
   "国際文化研究科"
  ],
  "fields":[
   "Letters"
  ],
  "themes":[
   "climate",
   "sustainability"
  ],
  "themes_scores":[
   2,
   2
  ],
  "matched_courses":[
   "km18840",
   "km12320",
   "km12490",
   "km28820"
  ],
  "nb_dedicated_courses":0
 },
 {
  "id":"b_nougaku",
  "name":"農学部（学士）",
  "cycle":"bac",
  "url":"https:\/\/qsl.cds.tohoku.ac.jp\/qsl\/syllabus\/find?type=nougaku",
  "languages":[
   "ja",
   "other",
   "en"
  ],
  "campuses":[

  ],
  "faculties":[
   "農学部"
  ],
  "fields":[
   "Bio-Engineering"
  ],
  "themes":[
   "climate",
   "energy",
   "environment",
   "sustainability"
  ],
  "themes_scores":[
   1,
   1,
   2,
   4
  ],
  "matched_courses":[
   "ab1321",
   "ab2402",
   "ab2661",
   "ab17012",
   "ab2314",
   "ab1112"
  ],
  "nb_dedicated_courses":2
 },
 {
  "id":"m_nougaku",
  "name":"農学部（修士）",
  "cycle":"master",
  "url":"https:\/\/qsl.cds.tohoku.ac.jp\/qsl\/syllabus\/find?type=nougaku",
  "languages":[
   "ja",
   "other",
   "en"
  ],
  "campuses":[

  ],
  "faculties":[
   "農学部"
  ],
  "fields":[
   "Bio-Engineering"
  ],
  "themes":[
   "climate",
   "environment",
   "sustainability"
  ],
  "themes_scores":[
   2,
   2,
   2
  ],
  "matched_courses":[
   "am3001",
   "am1132",
   "am6002",
   "am1605",
   "am1331"
  ],
  "nb_dedicated_courses":1
 },
 {
  "id":"b_hougaku",
  "name":"法学部（学士）",
  "cycle":"bac",
  "url":"https:\/\/qsl.cds.tohoku.ac.jp\/qsl\/syllabus\/find?type=hougaku",
  "languages":[
   "ja",
   "en"
  ],
  "campuses":[

  ],
  "faculties":[
   "法学部"
  ],
  "fields":[
   "Law & Criminology"
  ],
  "themes":[
   "environment",
   "sustainability"
  ],
  "themes_scores":[
   1,
   1
  ],
  "matched_courses":[
   "jb51556",
   "jb80851"
  ],
  "nb_dedicated_courses":1
 },
 {
  "id":"m_hougaku",
  "name":"法学部（修士）",
  "cycle":"master",
  "url":"https:\/\/qsl.cds.tohoku.ac.jp\/qsl\/syllabus\/find?type=hougaku",
  "languages":[
   "ja",
   "other",
   "en"
  ],
  "campuses":[

  ],
  "faculties":[
   "法学部"
  ],
  "fields":[
   "Law & Criminology"
  ],
  "themes":[
   "environment",
   "sustainability"
  ],
  "themes_scores":[
   1,
   1
  ],
  "matched_courses":[
   "jm24750",
   "jm32425"
  ],
  "nb_dedicated_courses":0
 },
 {
  "id":"d_hougaku",
  "name":"法学部（博士）",
  "cycle":"doctor",
  "url":"https:\/\/qsl.cds.tohoku.ac.jp\/qsl\/syllabus\/find?type=hougaku",
  "languages":[
   "ja",
   "other",
   "en"
  ],
  "campuses":[

  ],
  "faculties":[
   "法学部"
  ],
  "fields":[
   "Law & Criminology"
  ],
  "themes":[
   "sustainability"
  ],
  "themes_scores":[
   1
  ],
  "matched_courses":[
   "jd1000313"
  ],
  "nb_dedicated_courses":0
 },
 {
  "id":"b_kyouikugaku",
  "name":"教育学部（学士）",
  "cycle":"bac",
  "url":"https:\/\/qsl.cds.tohoku.ac.jp\/qsl\/syllabus\/find?type=kyouikugaku",
  "languages":[
   "ja"
  ],
  "campuses":[

  ],
  "faculties":[
   "教育学部"
  ],
  "fields":[
   "Pedagogy"
  ],
  "themes":[
   "sustainability"
  ],
  "themes_scores":[
   1
  ],
  "matched_courses":[
   "pb12220"
  ],
  "nb_dedicated_courses":0
 },
 {
  "id":"m_kyouikugaku",
  "name":"教育学部（修士）",
  "cycle":"master",
  "url":"https:\/\/qsl.cds.tohoku.ac.jp\/qsl\/syllabus\/find?type=kyouikugaku",
  "languages":[
   "ja"
  ],
  "campuses":[

  ],
  "faculties":[
   "教育学部"
  ],
  "fields":[
   "Pedagogy"
  ],
  "themes":[
   "sustainability"
  ],
  "themes_scores":[
   3
  ],
  "matched_courses":[
   "pm530150",
   "pm230040",
   "pm330040"
  ],
  "nb_dedicated_courses":0
 },
 {
  "id":"d_kyouikugaku",
  "name":"教育学部（博士）",
  "cycle":"doctor",
  "url":"https:\/\/qsl.cds.tohoku.ac.jp\/qsl\/syllabus\/find?type=kyouikugaku",
  "languages":[
   "ja"
  ],
  "campuses":[

  ],
  "faculties":[
   "教育学部"
  ],
  "fields":[
   "Pedagogy"
  ],
  "themes":[
   "sustainability"
  ],
  "themes_scores":[
   1
  ],
  "matched_courses":[
   "pd000030"
  ],
  "nb_dedicated_courses":0
 },
 {
  "id":"m_igaku",
  "name":"医学部医学科（修士）",
  "cycle":"master",
  "url":"https:\/\/qsl.cds.tohoku.ac.jp\/qsl\/syllabus\/find?type=igaku",
  "languages":[
   "ja",
   "other",
   "en"
  ],
  "campuses":[

  ],
  "faculties":[
   "医学部医学科"
  ],
  "fields":[
   "Medecine & Health"
  ],
  "themes":[
   "climate",
   "environment",
   "sustainability"
  ],
  "themes_scores":[
   4,
   3,
   2
  ],
  "matched_courses":[
   "mm6017",
   "mm5020",
   "mm6006",
   "mm2418",
   "mm9028",
   "mm9019",
   "mm5006",
   "mm8027",
   "mm8067"
  ],
  "nb_dedicated_courses":2
 },
 {
  "id":"d_igaku",
  "name":"医学部医学科（博士）",
  "cycle":"doctor",
  "url":"https:\/\/qsl.cds.tohoku.ac.jp\/qsl\/syllabus\/find?type=igaku",
  "languages":[
   "ja",
   "other",
   "en"
  ],
  "campuses":[

  ],
  "faculties":[
   "医学部医学科"
  ],
  "fields":[
   "Medecine & Health"
  ],
  "themes":[
   "sustainability"
  ],
  "themes_scores":[
   1
  ],
  "matched_courses":[
   "md221"
  ],
  "nb_dedicated_courses":0
 },
 {
  "id":"b_rigaku",
  "name":"理学部（学士）",
  "cycle":"bac",
  "url":"https:\/\/qsl.cds.tohoku.ac.jp\/qsl\/syllabus\/find?type=rigaku",
  "languages":[
   "ja",
   "other",
   "en"
  ],
  "campuses":[

  ],
  "faculties":[
   "理学部"
  ],
  "fields":[
   "Science"
  ],
  "themes":[
   "climate",
   "environment",
   "resources",
   "sustainability"
  ],
  "themes_scores":[
   7,
   3,
   1,
   2
  ],
  "matched_courses":[
   "sb7102",
   "sb3250",
   "sb5181",
   "sb3120",
   "sb3263",
   "sb5218",
   "sb9214",
   "sb7207",
   "sb6114",
   "sb3140",
   "sb7201"
  ],
  "nb_dedicated_courses":3
 },
 {
  "id":"m_rigaku",
  "name":"理学部（修士）",
  "cycle":"master",
  "url":"https:\/\/qsl.cds.tohoku.ac.jp\/qsl\/syllabus\/find?type=rigaku",
  "languages":[
   "ja",
   "other",
   "en"
  ],
  "campuses":[

  ],
  "faculties":[
   "理学部"
  ],
  "fields":[
   "Science"
  ],
  "themes":[
   "climate",
   "environment",
   "sustainability"
  ],
  "themes_scores":[
   5,
   5,
   3
  ],
  "matched_courses":[
   "sm62003",
   "sm61026",
   "sm41011",
   "sm7201",
   "sm61014",
   "sm61007",
   "sm41009",
   "sm41005",
   "sm51001",
   "sm42007"
  ],
  "nb_dedicated_courses":3
 },
 {
  "id":"d_rigaku",
  "name":"理学部（博士）",
  "cycle":"doctor",
  "url":"https:\/\/qsl.cds.tohoku.ac.jp\/qsl\/syllabus\/find?type=rigaku",
  "languages":[
   "ja",
   "other",
   "en"
  ],
  "campuses":[

  ],
  "faculties":[
   "理学部"
  ],
  "fields":[
   "Science"
  ],
  "themes":[
   "climate",
   "environment",
   "sustainability"
  ],
  "themes_scores":[
   2,
   4,
   2
  ],
  "matched_courses":[
   "sd61016",
   "sd62001",
   "sd42002",
   "sd61005",
   "sd42003",
   "sd42005"
  ],
  "nb_dedicated_courses":3
 },
 {
  "id":"b_keizaigaku",
  "name":"経済学部（学士）",
  "cycle":"bac",
  "url":"https:\/\/qsl.cds.tohoku.ac.jp\/qsl\/syllabus\/find?type=keizaigaku",
  "languages":[
   "ja",
   "other"
  ],
  "campuses":[

  ],
  "faculties":[
   "経済学部"
  ],
  "fields":[
   "Economy"
  ],
  "themes":[
   "climate",
   "sustainability"
  ],
  "themes_scores":[
   1,
   3
  ],
  "matched_courses":[
   "eb206",
   "eb351",
   "eb201",
   "eb352"
  ],
  "nb_dedicated_courses":0
 },
 {
  "id":"b_kougaku",
  "name":"工学部（学士）",
  "cycle":"bac",
  "url":"https:\/\/qsl.cds.tohoku.ac.jp\/qsl\/syllabus\/find?type=kougaku",
  "languages":[
   "ja",
   "other",
   "en"
  ],
  "campuses":[

  ],
  "faculties":[
   "工学部"
  ],
  "fields":[
   "Engineering"
  ],
  "themes":[
   "climate",
   "energy",
   "environment",
   "resources",
   "sustainability"
  ],
  "themes_scores":[
   14,
   14,
   15,
   5,
   26
  ],
  "matched_courses":[
   "tb55111",
   "tb16134",
   "tb56091",
   "tb56301",
   "tb15081",
   "tb36071",
   "tb17341",
   "tb45011",
   "tb53061",
   "tb51001",
   "tb53091",
   "tb56111",
   "tb36011",
   "tb14032",
   "tb16288",
   "tb17301",
   "tb5310e",
   "tb17441",
   "tb56281",
   "tb45071",
   "tb55141",
   "tb55131",
   "tb25041",
   "tb16291",
   "tb31001",
   "tb14034",
   "tb14031",
   "tb61041",
   "tb14141",
   "tb14033",
   "tb55051",
   "tb17271",
   "tb28011",
   "tb56221",
   "tb54131",
   "tb65051",
   "tb17331",
   "tb61031"
  ],
  "nb_dedicated_courses":17
 },
 {
  "id":"m_kougaku",
  "name":"工学部（修士）",
  "cycle":"master",
  "url":"https:\/\/qsl.cds.tohoku.ac.jp\/qsl\/syllabus\/find?type=kougaku",
  "languages":[
   "ja",
   "other",
   "en"
  ],
  "campuses":[

  ],
  "faculties":[
   "工学部"
  ],
  "fields":[
   "Engineering"
  ],
  "themes":[
   "climate",
   "energy",
   "environment",
   "resources",
   "sustainability"
  ],
  "themes_scores":[
   4,
   7,
   7,
   1,
   12
  ],
  "matched_courses":[
   "tm60029000",
   "tm70040000",
   "tm10020000",
   "tm40021100",
   "tm80018100",
   "tm60030000",
   "tm50031800",
   "tm10064100",
   "tm70005000",
   "tm60028000",
   "tm10063000",
   "tm70006000",
   "tm40021000",
   "tm70041000",
   "tm40014000",
   "tm20001100",
   "tm80014000",
   "tm60005000",
   "tm70043000",
   "tm70042000"
  ],
  "nb_dedicated_courses":8
 },
 {
  "id":"d_kougaku",
  "name":"工学部（博士）",
  "cycle":"doctor",
  "url":"https:\/\/qsl.cds.tohoku.ac.jp\/qsl\/syllabus\/find?type=kougaku",
  "languages":[
   "ja",
   "other",
   "en"
  ],
  "campuses":[

  ],
  "faculties":[
   "工学部"
  ],
  "fields":[
   "Engineering"
  ],
  "themes":[
   "climate",
   "energy",
   "environment",
   "sustainability"
  ],
  "themes_scores":[
   2,
   2,
   2,
   3
  ],
  "matched_courses":[
   "td80012000",
   "td60008000",
   "td60001000",
   "td10018000",
   "td60005000",
   "td70005000",
   "td50001000"
  ],
  "nb_dedicated_courses":2
 },
 {
  "id":"b_bungaku",
  "name":"文学部（学士）",
  "cycle":"bac",
  "url":"https:\/\/qsl.cds.tohoku.ac.jp\/qsl\/syllabus\/find?type=bungaku",
  "languages":[
   "ja"
  ],
  "campuses":[

  ],
  "faculties":[
   "文学部"
  ],
  "fields":[
   "Letters"
  ],
  "themes":[
   "climate",
   "environment",
   "sustainability"
  ],
  "themes_scores":[
   2,
   13,
   2
  ],
  "matched_courses":[
   "lb98801",
   "lb62301",
   "lb329",
   "lb73",
   "lb326",
   "lb344",
   "lb523",
   "lb54301",
   "lb63201",
   "lb62310",
   "lb62408",
   "lb65305",
   "lb309",
   "lb319",
   "lb64301"
  ],
  "nb_dedicated_courses":0
 },
 {
  "id":"m_bungaku",
  "name":"文学部（修士）",
  "cycle":"master",
  "url":"https:\/\/qsl.cds.tohoku.ac.jp\/qsl\/syllabus\/find?type=bungaku",
  "languages":[
   "ja"
  ],
  "campuses":[

  ],
  "faculties":[
   "文学部"
  ],
  "fields":[
   "Letters"
  ],
  "themes":[
   "environment"
  ],
  "themes_scores":[
   5
  ],
  "matched_courses":[
   "lm22407",
   "lm23201",
   "lm24301",
   "lm22308",
   "lm22309"
  ],
  "nb_dedicated_courses":0
 },
 {
  "id":"b_zengaku",
  "name":"全学教育（学士）",
  "cycle":"bac",
  "url":"https:\/\/qsl.cds.tohoku.ac.jp\/qsl\/syllabus\/find?type=zengaku",
  "languages":[
   "ja",
   "other",
   "en"
  ],
  "campuses":[

  ],
  "faculties":[
   "全学教育"
  ],
  "fields":[
   "Other"
  ],
  "themes":[
   "climate",
   "energy",
   "environment",
   "resources",
   "sustainability"
  ],
  "themes_scores":[
   24,
   6,
   16,
   4,
   16
  ],
  "matched_courses":[
   "cb45201",
   "cb31315",
   "cb14206",
   "cb00078",
   "cb55205",
   "cb00099",
   "cb00115",
   "cb00064",
   "cb11112",
   "cb11208",
   "cb11108",
   "cb00101",
   "cb45401",
   "cb31309",
   "cb14212",
   "cb00084",
   "cb24112",
   "cb21206",
   "cb11213",
   "cb21110",
   "cb00070",
   "cb51208",
   "cb11110",
   "cb24111",
   "cb23111",
   "cb34324",
   "cb24209",
   "cb24114",
   "cb00123",
   "cb00027",
   "cb31211",
   "cb00008",
   "cb24307",
   "cb32209",
   "cb11106",
   "cb33305",
   "cb31210",
   "cb11209",
   "cb24113",
   "cb45206",
   "cb31107",
   "cb22304"
  ],
  "nb_dedicated_courses":2
 }
]